Metadata-Version: 1.1
Name: djangopatchy
Version: 0.0.8
Summary: Useful django patch for large project
Home-page: UNKNOWN
Author: Fu Jian
Author-email: fujian_en@126.com
License: MIT
Platform: UNKNOWN
Classifier: Framework :: Django
Classifier: Environment :: Web Environment
Classifier: Intended Audience :: Developers
Classifier: License :: OSI Approved :: MIT License
Classifier: Operating System :: OS Independent
Classifier: Programming Language :: Python
Classifier: Topic :: Internet :: WWW/HTTP
